cubchoo/__init__.py
cubchoo/converters.py
cubchoo/errors.py
cubchoo/type_mappings.py
cubchoo-0.1.0.dist-info/licenses/LICENSE
cubchoo-0.1.0.dist-info/METADATA
cubchoo-0.1.0.dist-info/WHEEL
cubchoo-0.1.0.dist-info/top_level.txt
cubchoo-0.1.0.dist-info/RECORD
