Metadata-Version: 2.4
Name: cubchoo
Version: 0.1.0
Summary: Convert between Pandas and Polars schemas with ease
Author-email: Odos Matthews <odosmatthews@gmail.com>
License: MIT
Project-URL: Homepage, https://github.com/eddiethedean/cubchoo
Project-URL: Repository, https://github.com/eddiethedean/cubchoo
Project-URL: Issues, https://github.com/eddiethedean/cubchoo/issues
Keywords: pandas,polars,schema,conversion,dataframe
Classifier: Development Status :: 3 - Alpha
Classifier: Intended Audience :: Developers
Classifier: License :: OSI Approved :: MIT License
Classifier: Programming Language :: Python :: 3
Classifier: Programming Language :: Python :: 3.8
Classifier: Programming Language :: Python :: 3.9
Classifier: Programming Language :: Python :: 3.10
Classifier: Programming Language :: Python :: 3.11
Classifier: Programming Language :: Python :: 3.12
Classifier: Topic :: Software Development :: Libraries :: Python Modules
Classifier: Topic :: Scientific/Engineering :: Information Analysis
Requires-Python: >=3.8
License-File: LICENSE
Requires-Dist: pandas>=1.3.0
Requires-Dist: polars>=0.19.0
Provides-Extra: dev
Requires-Dist: pytest>=7.0.0; extra == "dev"
Requires-Dist: pytest-cov>=4.0.0; extra == "dev"
Requires-Dist: black>=23.0.0; extra == "dev"
Requires-Dist: ruff>=0.1.0; extra == "dev"
Requires-Dist: hypothesis>=6.0.0; extra == "dev"
Provides-Extra: pyarrow
Requires-Dist: pyarrow>=10.0.0; extra == "pyarrow"
Provides-Extra: all
Requires-Dist: cubchoo[dev,pyarrow]; extra == "all"
Dynamic: license-file
